scm203lab267112755/__init__.py
scm203lab267112755/lab2mod167112755.py
scm203lab267112755/lab2mod267112755.py
scm203lab267112755-0.1.2.dist-info/METADATA
scm203lab267112755-0.1.2.dist-info/WHEEL
scm203lab267112755-0.1.2.dist-info/top_level.txt
scm203lab267112755-0.1.2.dist-info/RECORD
