Metadata-Version: 2.4
Name: scm203lab267112755
Version: 0.1.2
Summary: Numerical methods: root finding and ODE solvers (Secant, False Position, Runge-Kutta).
Home-page: https://github.com/yourusername/mypackage
Author: Lewan
Author-email: natthapong.nn@mail.wu.ac.th
Requires-Python: >=3.7
Dynamic: author
Dynamic: author-email
Dynamic: description
Dynamic: description-content-type
Dynamic: home-page
Dynamic: requires-python
Dynamic: summary
